bookalimo/__init__.py
bookalimo/_version.py
bookalimo/client.py
bookalimo/config.py
bookalimo/exceptions.py
bookalimo/logging.py
bookalimo/py.typed
bookalimo/integrations/__init__.py
bookalimo/integrations/google_places/__init__.py
bookalimo/integrations/google_places/client_async.py
bookalimo/integrations/google_places/client_sync.py
bookalimo/integrations/google_places/common.py
bookalimo/integrations/google_places/proto_adapter.py
bookalimo/integrations/google_places/resolve_airport.py
bookalimo/integrations/google_places/transports.py
bookalimo/schemas/__init__.py
bookalimo/schemas/base.py
bookalimo/schemas/requests.py
bookalimo/schemas/responses.py
bookalimo/schemas/shared.py
bookalimo/schemas/places/__init__.py
bookalimo/schemas/places/common.py
bookalimo/schemas/places/field_mask.py
bookalimo/schemas/places/google.py
bookalimo/schemas/places/place.py
bookalimo/services/__init__.py
bookalimo/services/pricing.py
bookalimo/services/reservations.py
bookalimo/transport/__init__.py
bookalimo/transport/auth.py
bookalimo/transport/base.py
bookalimo/transport/httpx_async.py
bookalimo/transport/httpx_sync.py
bookalimo/transport/retry.py
bookalimo/transport/utils.py
bookalimo-1.0.2.dist-info/licenses/LICENSE
bookalimo-1.0.2.dist-info/METADATA
bookalimo-1.0.2.dist-info/WHEEL
bookalimo-1.0.2.dist-info/top_level.txt
bookalimo-1.0.2.dist-info/RECORD
