Metadata-Version: 2.4
Name: bookalimo
Version: 1.0.2
Summary: Python wrapper for the Book-A-Limo API
Author-email: Jonathan Oren <jonathan@bookalimo.com>
Maintainer-email: Jonathan Oren <jonathan@bookalimo.com>
License: MIT
Project-URL: Homepage, https://github.com/asparagusbeef/bookalimo-python
Project-URL: Documentation, https://asparagusbeef.github.io/bookalimo-python
Project-URL: Repository, https://github.com/asparagusbeef/bookalimo-python
Project-URL: Issues, https://github.com/asparagusbeef/bookalimo-python/issues
Project-URL: Changelog, https://github.com/asparagusbeef/bookalimo-python/blob/main/CHANGELOG.md
Keywords: bookalimo,api,transportation,booking
Classifier: Development Status :: 3 - Alpha
Classifier: Intended Audience :: Developers
Classifier: License :: OSI Approved :: MIT License
Classifier: Operating System :: OS Independent
Classifier: Programming Language :: Python :: 3
Classifier: Programming Language :: Python :: 3.9
Classifier: Programming Language :: Python :: 3.10
Classifier: Programming Language :: Python :: 3.11
Classifier: Programming Language :: Python :: 3.12
Classifier: Programming Language :: Python :: 3.13
Classifier: Topic :: Software Development :: Libraries :: Python Modules
Classifier: Topic :: Internet :: WWW/HTTP :: Dynamic Content
Requires-Python: >=3.9
License-File: LICENSE
Requires-Dist: httpx>=0.25.0
Requires-Dist: pydantic>=2.11.0
Requires-Dist: pycountry>=22.0.0
Requires-Dist: us>=3.0.0
Requires-Dist: airportsdata>=20230101
Provides-Extra: places
Requires-Dist: google-maps-places>=0.1.0; extra == "places"
Requires-Dist: google-api-core>=2.0.0; extra == "places"
Requires-Dist: numpy>=2.0.0; extra == "places"
Requires-Dist: rapidfuzz>=3.0.0; extra == "places"
Requires-Dist: typing-extensions>=4.15.0; python_version < "3.11" and extra == "places"
Provides-Extra: dev
Requires-Dist: pytest>=7.0.0; extra == "dev"
Requires-Dist: pytest-asyncio>=0.21.0; extra == "dev"
Requires-Dist: pytest-cov>=4.0.0; extra == "dev"
Requires-Dist: pytest-mock>=3.10.0; extra == "dev"
Requires-Dist: httpx[mock]>=0.25.0; extra == "dev"
Requires-Dist: respx>=0.20.0; extra == "dev"
Requires-Dist: ruff>=0.1.0; extra == "dev"
Requires-Dist: mypy>=1.5.0; extra == "dev"
Requires-Dist: pre-commit>=3.0.0; extra == "dev"
Requires-Dist: build>=1.0.0; extra == "dev"
Requires-Dist: twine>=4.0.0; extra == "dev"
Requires-Dist: python-dotenv>=1.0.0; extra == "dev"
Requires-Dist: types-protobuf>=6.0.0; extra == "dev"
Provides-Extra: test
Requires-Dist: pytest>=7.0.0; extra == "test"
Requires-Dist: pytest-asyncio>=0.21.0; extra == "test"
Requires-Dist: pytest-cov>=4.0.0; extra == "test"
Requires-Dist: pytest-mock>=3.10.0; extra == "test"
Requires-Dist: httpx[mock]>=0.25.0; extra == "test"
Requires-Dist: respx>=0.20.0; extra == "test"
Dynamic: license-file
